tabloid
