Metadata-Version: 1.0
Name: tabloid
Version: 0.2
Summary: Make your terminal pretty
Home-page: https://github.com/shoonoise/tabloid
Author: Alexander Kushnarev
Author-email: avkushnarev@gmail.com
License: UNKNOWN
Platform: UNKNOWN
